odoo/addons/web_tree_customized_field_list/README.rst
odoo/addons/web_tree_customized_field_list/__init__.py
odoo/addons/web_tree_customized_field_list/__manifest__.py
odoo/addons/web_tree_customized_field_list/hooks.py
odoo/addons/web_tree_customized_field_list/i18n/it.po
odoo/addons/web_tree_customized_field_list/i18n/web_tree_customized_field_list.pot
odoo/addons/web_tree_customized_field_list/models/__init__.py
odoo/addons/web_tree_customized_field_list/models/custom_list.py
odoo/addons/web_tree_customized_field_list/models/customer_list_view_line.py
odoo/addons/web_tree_customized_field_list/models/ir_module.py
odoo/addons/web_tree_customized_field_list/models/ir_ui_view.py
odoo/addons/web_tree_customized_field_list/readme/CONTRIBUTORS.rst
odoo/addons/web_tree_customized_field_list/readme/DESCRIPTION.rst
odoo/addons/web_tree_customized_field_list/readme/ROADMAP.rst
odoo/addons/web_tree_customized_field_list/readme/USAGE.rst
odoo/addons/web_tree_customized_field_list/security/ir.model.access.csv
odoo/addons/web_tree_customized_field_list/static/description/icon.png
odoo/addons/web_tree_customized_field_list/tests/__init__.py
odoo/addons/web_tree_customized_field_list/tests/test_customized_list_view.py
odoo/addons/web_tree_customized_field_list/views/views.xml
odoo14_addon_web_tree_customized_field_list-14.0.1.0.1.dev5.dist-info/METADATA
odoo14_addon_web_tree_customized_field_list-14.0.1.0.1.dev5.dist-info/WHEEL
odoo14_addon_web_tree_customized_field_list-14.0.1.0.1.dev5.dist-info/top_level.txt
odoo14_addon_web_tree_customized_field_list-14.0.1.0.1.dev5.dist-info/RECORD
