Metadata-Version: 2.1
Name: odoo14-addon-web_tree_customized_field_list
Version: 14.0.1.0.1.dev5
Summary: Add fields into list view
Home-page: https://github.com/OCA/server-ux
Author: Ilyas, Ooops, Odoo Community Association (OCA)
Author-email: support@odoo-community.org
License: AGPL-3
Classifier: Programming Language :: Python
Classifier: Framework :: Odoo
Classifier: Framework :: Odoo :: 14.0
Classifier: License :: OSI Approved :: GNU Affero General Public License v3
Requires-Python: >=3.6
Requires-Dist: odoo14-addon-web-domain-field
Requires-Dist: odoo<14.1dev,>=14.0a
